<vra xmlns="http://www.vraweb.org/vracore4.htm" xmlns:xsi="http://www.w3.org/2001/XMLSchema-instance" xsi:schemaLocation="http://www.vraweb.org/vracore4.htm http://cluster-schemas.uni-hd.de/vra-strictCluster.xsd" xmlns:hra="http://cluster-schemas.uni-hd.de" >
	<work id="w_0c4eb87e-3a2f-55d6-873b-6fe817209b31" source="EXC Priya Paul Collection" refid="c_b9827ec8-6b66-5d98-9f5e-ca12b58044c4">
		<agentSet>
			<agent>
				<name vocab="local" type="personal" refid="uuid-2d9170ef-2e41-537c-8a78-28b7be563ae7">Paul, Priya</name>
				<role vocab="marcrelator" code="col">Collector</role>
			</agent>
			<agent>
				<culture/>
				<name vocab="local" type="corporate" refid="uuid-7c4f8f3b-8489-5329-a79b-b444e8e10d04">West Bengal Stores</name>
				<role/>
  			</agent>
		</agentSet>
 		<dateSet>
			<date type="creation">
				<earliestDate>1955</earliestDate>
				<latestDate>1955</latestDate>
			</date>
		</dateSet>
		<locationSet>
			<location type="repository">
				<name type="corporate" vocab="local">Delhi / The Priya Paul Collection of Popular Art</name>
				<refid/>
			</location>
			<location source="EXC" type="repository">
				<name type="geographic" vocab="local" refid="511">Delhi / The Priya Paul Collection of Popular Art</name>
			</location>
		</locationSet>
		<relationSet>
			<relation type="imageIs" relids="i_7e4d0ad9-c8a1-55f6-b66f-a5c87d4e29bb" refid="139299" source="EXC Priya Paul Collection" pref="true"></relation>
		</relationSet>
		<rightsSet>
			<rights type="copyrighted">
				<rightsHolder/>
				<text>Copyrighted. Copyright with the original artists and publishers.</text>
			</rights>
		</rightsSet>
		<titleSet>
			<title type="descriptive" pref="true" lang="en" script="latn">Howrah Bridge</title>
		</titleSet>
		<worktypeSet>
			<worktype vocab="local" source="EXC" refid="37e0ef55-0bad-54b1-8ded-1082206c6016">calendars</worktype>
		</worktypeSet>
		<hra:heidicon>
			<hra:item type="f_description" status="0"  display="Description">
				<hra:value>Calendar of West Bengal Stores showing  the &quot;Howrah Bridge&quot;, the &quot;Hoogly&quot; river and the traffic. The calendar shows the month of January and it is a tear-away page for each month. There are two small images to bottom left and bottom right of the calendar.</hra:value>
			</hra:item>
		</hra:heidicon>
		<hra:heidicon>
			<hra:item type="f_description" status="0"  display="Kommentar">
				<hra:value>explanatory comments/crosstagging:
20090901_3200</hra:value>
			</hra:item>
		</hra:heidicon>
		<hra:heidicon>
			<hra:item type="f_id_heidicon" status="0" display="Heidicon image_id">
				<hra:value>http://heidicon.ub.uni-heidelberg.de/id/139299</hra:value>
				<hra:value>139299</hra:value>
			</hra:item>
		</hra:heidicon>
		<hra:heidicon>
			<hra:administrative type="heidicon2vra" date="2013-01-23 14:47:07">
			</hra:administrative>
		</hra:heidicon>
	</work>
</vra>