<vra xmlns="http://www.vraweb.org/vracore4.htm" xmlns:xsi="http://www.w3.org/2001/XMLSchema-instance" xsi:schemaLocation="http://www.vraweb.org/vracore4.htm http://cluster-schemas.uni-hd.de/vra-strictCluster.xsd" xmlns:ext="http://exist-db.org/vra/extension">
	<work id="w_3ca9b66b-beb9-5da5-b7b3-8190a34aeb35" source="EXC Priya Paul Collection" refid="c_b9827ec8-6b66-5d98-9f5e-ca12b58044c4">
		<agentSet>
			<agent>
				<name vocab="local" type="personal" refid="uuid-2d9170ef-2e41-537c-8a78-28b7be563ae7">Paul, Priya</name>
				<role vocab="marcrelator" type="code">col</role>
			</agent>
			<agent>
				<culture/>
				<name vocab="local" type="personal" refid="uuid-6a2e3bc2-f7f2-534f-bcac-5870a237313e">Ravi Varma, Raja</name>
				<role vocab="marcrelator" type="code">art</role>
  			</agent>
			<agent>
				<culture/>
				<name vocab="local" type="corporate" refid="uuid-46ab475d-6467-58f7-83df-ecdac56fb468">The Bombay Company Ltd.</name>
				<role vocab="marcrelator" type="code">cli</role>
  			</agent>
			<agent>
				<culture/>
				<name vocab="local" type="corporate" refid="uuid-debc21eb-564b-52f1-97d2-f48a73c3b6b9">Oriental Calendar Manufacturing Company</name>
				<role vocab="marcrelator" type="code">cli</role>
  			</agent>
		</agentSet>
		<descriptionSet>
			<description lang="eng" script="Latn">
				<text>This textile label from the Bombay Company Ltd. shows a woman in a red sari climbing up the steps to a  temple.  A sculpture of a cow can be seen near the entrance of the temple. &quot;Delhi Karachi Amritsar&quot; and &quot;The Bombay Company Ltd.&quot; is written along the edges of the image in English as well as Devanagari. This image is a replica of a Ravi Varma painting.</text>
				<author>
					<name vocab="local" type="personal" refid="uuid-d4f4f076-3fb9-5544-95bf-29ba8cb16992">Schoenhofer, Gerhard</name>
					<role vocab="marcrelator" code="edt">Editor</role>
				</author>
				<author>
					<name vocab="local" type="personal" refid="uuid-dc8e6805-ec52-547a-993f-586ebd9681cc">Padmanabhan, Sridevi</name>
					<role vocab="marcrelator" code="edt">Editor</role>
				</author>
			</description>
		</descriptionSet>
		<inscriptionSet>
			<inscription>
				<text type="text" lang="eng">The Bombay Company Limited</text>
			</inscription>
			<inscription>
				<text type="text" lang="eng">Delhi Karachi Amritsar.</text>
			</inscription>
			<inscription>
				<text type="text" lang="hin">देहली-अमृतसर- क्राची</text>
			</inscription>
			<inscription>
				<text type="text" lang="hin">धी  बाम्बे कंपनी लीमीटेड</text>
			</inscription>
		</inscriptionSet>
		<locationSet>
			<location source="EXC" type="repository">
				<name type="corporate" vocab="local" refid="uuid-1544a228-b79f-5cd9-a2ac-ff357ef3da5b">Delhi / The Priya Paul Collection of Popular Art</name>
			</location>
			<location source="EXC" type="repository">
				<name type="geographic" vocab="local" refid="">Delhi / The Priya Paul Collection of Popular Art</name>
			</location>
		</locationSet>
		<materialSet>
			<material vocab="LOCAL" refid="ce497196-b1b5-52ee-9f08-bb6627e56ef2" type="medium">paper (fiber product)</material>
		</materialSet>
		<relationSet>
			<relation type="imageIs" relids="i_edebc20a-6643-5766-b1d3-b1479f1f1108" refid="106168" source="EXC Priya Paul Collection" pref="true">general view</relation>
		</relationSet>
		<rightsSet>
			<rights type="copyrighted">
				<rightsHolder/>
				<text>Copyrighted. Copyright with the original artists and publishers.</text>
			</rights>
		</rightsSet>
 		<sourceSet>
		</sourceSet>
		<stylePeriodSet>
			<stylePeriod>late 19th century</stylePeriod>
		</stylePeriodSet>
		<subjectSet>
			<subject source="EXC" vocab="LOCAL" refid="b4de6888-0ad1-5d98-a569-35967541f46f">
				<term type="conceptTopic">worship</term>
			</subject>
			<subject source="EXC" vocab="LOCAL" refid="32a1aacf-64a3-569d-affd-44ed9e8d90e7">
				<term type="descriptiveTopic">temples (buildings)</term>
			</subject>
			<subject source="EXC" vocab="LOCAL" refid="98cdd292-9b30-5297-a6f8-99dfdfc40644">
				<term type="descriptiveTopic">red sari</term>
			</subject>
			<subject source="EXC" vocab="LOCAL" refid="2e729391-6532-52d8-8683-1602a3277fec">
				<term type="descriptiveTopic">red (color)</term>
			</subject>
			<subject source="EXC" vocab="LOCAL" refid="e1843b1e-dbc3-59fa-862b-ad2576503b22">
				<term type="descriptiveTopic">cows</term>
			</subject>
			<subject source="EXC" vocab="LOCAL" refid="b64e275b-fe28-50db-a1e8-63a7fc7d0a85">
				<term type="descriptiveTopic">textile label</term>
			</subject>
			<subject source="EXC" vocab="LOCAL" refid="27dcc0d5-5d98-5d7e-bc64-2ee2b0760693">
				<term type="conceptTopic">Hindu women</term>
			</subject>
			<subject source="EXC" vocab="LOCAL" refid="ec448b73-22cd-57e0-b986-e02942411d1f">
				<term type="descriptiveTopic">saris (garments)</term>
			</subject>
			<subject source="EXC" vocab="LOCAL" refid="f0a66022-0cfc-5969-9867-775c451e34d3">
				<term type="conceptTopic">Bharatiya Nari</term>
			</subject>
			<subject source="EXC" vocab="LOCAL" refid="bb1d842f-4b29-5eee-a085-269d58cd6cb4">
				<term type="otherTopic">recheck</term>
			</subject>
			<subject source="EXC" vocab="LOCAL" refid="c06dd31c-01d4-52fc-90ae-47a10d6519db">
				<term type="otherTopic">recheck-Medialab</term>
			</subject>
			<subject source="EXC" vocab="LOCAL" refid="d7e59f38-e7d8-54bf-91b8-d16cc4f9ba81">
				<term type="otherTopic">recheck-problem</term>
			</subject>
			<subject source="EXC" vocab="LOCAL" refid="987839c1-73e5-5c70-aec8-9826da6fe83a">
				<term type="otherTopic">recheck-original-language</term>
			</subject>
			<subject source="EXC" vocab="LOCAL" refid="9b2c09f3-f24a-5c77-bbdb-b15cc1310764">
				<term type="descriptiveTopic">scripts (writing)</term>
			</subject>
			<subject source="EXC" vocab="LOCAL" refid="0fdaf619-0e7c-5cab-8167-d0b3cc1cd392">
				<term type="otherTopic">Devanagari script</term>
			</subject>
			<subject source="EXC" vocab="LOCAL" refid="e38635c9-239d-529e-b2ef-09d0617e47a8">
				<term type="conceptTopic">perception of women</term>
			</subject>
		</subjectSet>
		<techniqueSet>
			<technique vocab="LOCAL" refid="05e81717-b5c1-552f-bafc-950a0f1ad2df">chromolithographs</technique>
		</techniqueSet>
		<titleSet>
			<title type="descriptive" pref="true" lang="eng" script="Latn">Textile label by The Bombay Company Limited</title>
			<title type="descriptive" pref="false">देहली-अमृतसर- क्राची</title>
		</titleSet>
		<worktypeSet>
			<worktype vocab="local" source="EXC" refid="b64e275b-fe28-50db-a1e8-63a7fc7d0a85">textile label</worktype>
		</worktypeSet>
		<ext:heidicon>
			<ext:item type="f_description" status="0"  display="Full_Description">
				<ext:value>text-en:
The Bombay Company Limited</ext:value>
				<ext:value>text-en:
Delhi Karachi Amritsar.</ext:value>
				<ext:value>text-hi:
देहली-अमृतसर- क्राची</ext:value>
				<ext:value>text-hi:
धी  बाम्बे कंपनी लीमीटेड</ext:value>
				<ext:value>description-en:
This textile label from the Bombay Company Ltd. shows a woman in a red sari climbing up the steps to a  temple.  A sculpture of a cow can be seen near the entrance of the temple. &quot;Delhi Karachi Amritsar&quot; and &quot;The Bombay Company Ltd.&quot; is written along the edges of the image in English as well as Devanagari. This image is a replica of a Ravi Varma painting. (gs/sp)</ext:value>
			</ext:item>
		</ext:heidicon>
		<ext:heidicon>
			<ext:item type="f_description" status="0"  display="Full_Commentary">
				<ext:value>explanatory comments/crosstagging:
For this image, there is clearly an ethnographic sense of documenting the practices of Indian women, in a context complete with cow and temple. (Sandria B. Freitag)(gs)</ext:value>
				<ext:value>explanatory comments/crosstagging:
Daily worship (especially by wives on behalf of the family), at home or in appropriate sacred spaces (temples, shrines), is among the most obvious of everyday activities, not least because of its connections to the myriad god-posters that swell the panoply of popular visual-culture artifacts.  Given the extensive work that has been devoted to this subject, we pause here only to note what happens when women/ wives are added to the picturing of the gods, which clearly shifts the sense of connection. (Sandria B. Freitag)(gs)</ext:value>
				<ext:value>related literature:
Braudel, Fernand 1981. &quot;The Structures of Everyday Life&quot;. London: Collins. (gs)</ext:value>
				<ext:value>related literature:
de Certeau, Michel 1984. &quot;The Practices of Everyday Life&quot; . Berkeley: University of California Press. (gs)</ext:value>
				<ext:value>related literature:
Freitag, Sandria B. 2010. &quot;Consumption and identity: Imagining ‘Everyday Life’ Through Popular Visual Culture&quot; (gs)</ext:value>
				<ext:value>related hyperlinks:
http://www.tasveergharindia.net/cmsdesk/essay/96/index.html last accessed 2011-04-13, Tasveer Ghar essay (gs)</ext:value>
				<ext:value>related literature:
Thanvi, Asraf Ali 1990. &quot;Perfecting Women&quot;. Berkley: University of California Press. (gs)</ext:value>
			</ext:item>
		</ext:heidicon>
		<ext:heidicon>
			<ext:item type="t_rl" status="0" display="comment:related_literature">
				<ext:value type="text">uuid-63c2d3a9-05af-3a34-af31-08461e16c98d</ext:value>
				<ext:item type="agent">
					<ext:value type="role">Editor</ext:value>
					<ext:value type="name">Schoenhofer, Gerhard</ext:value>
					<ext:value type="agent-type">personal</ext:value>
					<ext:value type="refid">uuid-d4f4f076-3fb9-5544-95bf-29ba8cb16992</ext:value>
				</ext:item>
			</ext:item>
			<ext:item type="t_rl" status="0" display="comment:related_literature">
				<ext:value type="text">uuid-c1faf8e6-0275-3799-8bc7-5de8dc2f219e</ext:value>
				<ext:item type="agent">
					<ext:value type="role">Editor</ext:value>
					<ext:value type="name">Schoenhofer, Gerhard</ext:value>
					<ext:value type="agent-type">personal</ext:value>
					<ext:value type="refid">uuid-d4f4f076-3fb9-5544-95bf-29ba8cb16992</ext:value>
				</ext:item>
			</ext:item>
			<ext:item type="t_rl" status="0" display="comment:related_literature">
				<ext:value type="text">uuid-9715bfc0-a84e-3de3-994c-bd987eef067e</ext:value>
				<ext:item type="agent">
					<ext:value type="role">Editor</ext:value>
					<ext:value type="name">Schoenhofer, Gerhard</ext:value>
					<ext:value type="agent-type">personal</ext:value>
					<ext:value type="refid">uuid-d4f4f076-3fb9-5544-95bf-29ba8cb16992</ext:value>
				</ext:item>
			</ext:item>
			<ext:item type="t_rl" status="0" display="comment:related_literature">
				<ext:value type="text">uuid-84d6aee2-b3ee-3120-9923-3416c5ed7b3b</ext:value>
				<ext:item type="agent">
					<ext:value type="role">Editor</ext:value>
					<ext:value type="name">Schoenhofer, Gerhard</ext:value>
					<ext:value type="agent-type">personal</ext:value>
					<ext:value type="refid">uuid-d4f4f076-3fb9-5544-95bf-29ba8cb16992</ext:value>
				</ext:item>
			</ext:item>
		</ext:heidicon>
		<ext:heidicon>
			<ext:item type="t_rh" status="0" display="comment:related_hyperlinks">
				<ext:value type="url">uuid-c1faf8e6-0275-3799-8bc7-5de8dc2f219e</ext:value>
				<ext:value type="accessed">2011-04-13</ext:value>
				<ext:value type="comment">Tasveer Ghar essay</ext:value>
				<ext:item type="agent">
					<ext:value type="role">Editor</ext:value>
					<ext:value type="name">Schoenhofer, Gerhard</ext:value>
					<ext:value type="agent-type">personal</ext:value>
					<ext:value type="refid">uuid-d4f4f076-3fb9-5544-95bf-29ba8cb16992</ext:value>
				</ext:item>
			</ext:item>
		</ext:heidicon>
		<ext:heidicon>
			<ext:item type="t_ecs" status="0" display="comment:explanatory_comments_crosstagging">
				<ext:value type="text">For this image, there is clearly an ethnographic sense of documenting the practices of Indian women, in a context complete with cow and temple.</ext:value>
				<ext:item type="agent">
					<ext:value type="role">Author</ext:value>
					<ext:value type="name">Sandria B. Freitag</ext:value>
					<ext:value type="agent-type">personal</ext:value>
					<ext:value type="refid">$UUID$</ext:value>
				</ext:item>
				<ext:item type="agent">
					<ext:value type="role">Editor</ext:value>
					<ext:value type="name">Schoenhofer, Gerhard</ext:value>
					<ext:value type="agent-type">personal</ext:value>
					<ext:value type="refid">uuid-d4f4f076-3fb9-5544-95bf-29ba8cb16992</ext:value>
				</ext:item>
			</ext:item>
			<ext:item type="t_ecs" status="0" display="comment:explanatory_comments_crosstagging">
				<ext:value type="text">Daily worship (especially by wives on behalf of the family), at home or in appropriate sacred spaces (temples, shrines), is among the most obvious of everyday activities, not least because of its connections to the myriad god-posters that swell the panoply of popular visual-culture artifacts.  Given the extensive work that has been devoted to this subject, we pause here only to note what happens when women/ wives are added to the picturing of the gods, which clearly shifts the sense of connection.</ext:value>
				<ext:item type="agent">
					<ext:value type="role">Author</ext:value>
					<ext:value type="name">Sandria B. Freitag</ext:value>
					<ext:value type="agent-type">personal</ext:value>
					<ext:value type="refid">$UUID$</ext:value>
				</ext:item>
				<ext:item type="agent">
					<ext:value type="role">Editor</ext:value>
					<ext:value type="name">Schoenhofer, Gerhard</ext:value>
					<ext:value type="agent-type">personal</ext:value>
					<ext:value type="refid">uuid-d4f4f076-3fb9-5544-95bf-29ba8cb16992</ext:value>
				</ext:item>
			</ext:item>
		</ext:heidicon>

		<ext:heidicon>
			<ext:item type="f_id_heidicon" status="0" display="Heidicon image_id">
				<ext:value>http://heidicon.ub.uni-heidelberg.de/id/106168</ext:value>
				<ext:value>106168</ext:value>
			</ext:item>
		</ext:heidicon>
		<ext:heidicon>
			<ext:administrative type="heidicon2vra" date="2014-01-15T17:56:33">
			</ext:administrative>
		</ext:heidicon>
	</work>
</vra>