<vra xmlns="http://www.vraweb.org/vracore4.htm" xmlns:xsi="http://www.w3.org/2001/XMLSchema-instance" xsi:schemaLocation="http://www.vraweb.org/vracore4.htm http://cluster-schemas.uni-hd.de/vra-strictCluster.xsd" xmlns:ext="http://exist-db.org/vra/extension">
	<work id="w_49b9e77a-5804-5e01-93d6-d630dbb2a88f" source="EXC Priya Paul Collection" refid="c_b9827ec8-6b66-5d98-9f5e-ca12b58044c4">
		<agentSet>
			<agent>
				<name vocab="local" type="personal" refid="uuid-2d9170ef-2e41-537c-8a78-28b7be563ae7">Paul, Priya</name>
				<role vocab="marcrelator" type="code">col</role>
			</agent>
			<agent>
				<culture/>
				<name vocab="local" type="corporate" refid="uuid-b3ad4894-fb33-52b9-ae64-e87471c9aec7">A &amp; F Harvey</name>
				<role vocab="marcrelator" type="code">cli</role>
  			</agent>
			<agent>
				<culture/>
				<name vocab="local" type="corporate" refid="uuid-e7213ed9-ad38-55b8-bff8-ca845c6aa105">Madura Mills Co. Ltd.</name>
				<role vocab="marcrelator" type="code">cli</role>
  			</agent>
		</agentSet>
		<descriptionSet>
			<description vocab="LOCAL" refid="687bd7ca-1185-5511-8938-1f351c94a5eb">framing (processes)</description>
		</descriptionSet>
		<inscriptionSet>
			<inscription>
				<text type="text" lang="en">A &amp; F Harvey
Merchants and cotton spinners</text>
			</inscription>
			<inscription>
				<text type="text" lang="en">Counts up to 80's
Single Yarns
Double Yarns</text>
			</inscription>
			<inscription>
				<text type="text" lang="en">Cone Yarns
Cheese Yarns
Cord &amp; Fancy Yarns</text>
			</inscription>
			<inscription>
				<text type="text" lang="en">cone yarn
Madura Mills co. Ltd.
20 s
Madura</text>
			</inscription>
			<inscription>
				<text type="text" lang="en">cheese yarn
Madura Mills Co. Ltd.
24 s
Madura
Cohal Mills Co. Ltd
Ring No</text>
			</inscription>
			<inscription>
				<text type="text" lang="en">With the Compliments of
Madura Mills Co. Ltd.
[isncription on arch in central image]</text>
			</inscription>
			<inscription>
				<text type="text" lang="en">The Arts School,
Madura.
[signature, central image]</text>
			</inscription>
			<inscription>
				<text type="text" lang="xx">PLEASE ADD ORIGINAL LANGUAGE HERE [below central image, left]</text>
			</inscription>
			<inscription>
				<text type="text" lang="en">Sree Meenakshisundareswarar, Madura
[below central image, middle]</text>
			</inscription>
			<inscription>
				<text type="text" lang="xx">PLEASE ADD ORIGINAL LANGUAGE HERE
[below central image, right]</text>
			</inscription>
			<inscription>
				<text type="text" lang="en">Madura Mills Company Limited.
Best Ring</text>
			</inscription>
			<inscription>
				<text type="text" lang="en">Tinnevelly Turbine Twist
Tinnevelly Mills Company Limited
Ring No.</text>
			</inscription>
			<inscription>
				<text type="text" lang="xx">PLEASE ADD ORIGINAL LANGUAGE HERE</text>
			</inscription>
			<inscription>
				<text type="text" lang="en">Madura Mills Co. Ltd.
Tuticorn, Madura &amp; Ambasamudram, South India</text>
			</inscription>
			<inscription>
				<text type="text" lang="xx">PLEASE ADD ORIGINAL LANGUAGE HERE</text>
			</inscription>
			<inscription>
				<text type="text" lang="en">London Correspondents
Harvey Brothers
Agency Ltd.
34 Queen Anne's Gate
Westminster
London
S. W. 1</text>
			</inscription>
			<inscription>
				<text type="text" lang="en">1941</text>
			</inscription>
			<inscription>
				<text type="text" lang="en">Tele Address SONPAL.
Phone: B. B. 1519
Yarns available from
Messrs
Mooljee Girdhardass
5, Noormull Lohia Lane
&amp;
176, cross Street,
Calcutta.</text>
			</inscription>
			<inscription>
				<text type="text" lang="en">Associated printers, Mount Road, Madras.</text>
			</inscription>
			<inscription>
				<text type="signature">The Arts School, Madura.</text>
			</inscription>
		</inscriptionSet>
		<locationSet>
			<location type="repository">
				<name type="corporate" vocab="local">Delhi / The Priya Paul Collection of Popular Art</name>
			</location>
			<location source="EXC" type="repository">
				<name type="geographic" vocab="local" refid="511">Delhi / The Priya Paul Collection of Popular Art</name>
			</location>
			<location type="formerRepository">
				<name vocab="local" refid="" href="http://heidicon.ub.uni-heidelberg.de/id/118512" type="corporate">HeidICON Image Database</name>
				<refid>118512</refid>
			</location>
		</locationSet>
		<materialSet>
			<material vocab="LOCAL" refid="ce497196-b1b5-52ee-9f08-bb6627e56ef2" type="medium">paper (fiber product)</material>
		</materialSet>
		<measurementsSet>
			<notes>38 cm x 50 cm, landscape</notes>
			<measurements type="height" unit="cm">38</measurements>
			<measurements type="width" unit="cm">50</measurements>
			<measurements shape="landscape" />
		</measurementsSet>
		<relationSet>
			<relation type="imageIs" relids="i_44473bd9-c80b-5441-90fb-fa1fc976b077" refid="118512" source="EXC Priya Paul Collection" pref="true">general view</relation>
			<relation type="imageIs" relids="i_3e1952fd-d564-5db5-8adb-26ae6995783d" refid="118514" source="EXC Priya Paul Collection">detail view</relation>
		</relationSet>
		<rightsSet>
			<rights type="copyrighted">
				<rightsHolder/>
				<text>Copyrighted. Copyright with the original artists and publishers.</text>
			</rights>
		</rightsSet>
		<subjectSet>
			<subject source="EXC" vocab="LOCAL" refid="fa6616f5-f242-521a-843c-c5b084cc7845">
				<term type="worktype">advertisements</term>
			</subject>
			<subject source="EXC" vocab="LOCAL" refid="e96f2402-7aa3-539e-99cf-6bce03f8b2b4">
				<term type="concept">product advertisement</term>
			</subject>
			<subject source="EXC" vocab="LOCAL" refid="e1843b1e-dbc3-59fa-862b-ad2576503b22">
				<term type="animal">cows</term>
			</subject>
			<subject source="EXC" vocab="LOCAL" refid="37e0ef55-0bad-54b1-8ded-1082206c6016">
				<term type="worktype">calendars</term>
			</subject>
			<subject source="EXC" vocab="LOCAL" refid="e38f299d-a3ca-5956-b7b6-c8f61581e43f">
				<term type="internal workflow">recheck-new</term>
			</subject>
			<subject source="EXC" vocab="LOCAL" refid="d7e59f38-e7d8-54bf-91b8-d16cc4f9ba81">
				<term type="internal workflow">recheck-problem</term>
			</subject>
			<subject source="EXC" vocab="LOCAL" refid="987839c1-73e5-5c70-aec8-9826da6fe83a">
				<term type="internal workflow">recheck-original-language</term>
			</subject>
		</subjectSet>
		<techniqueSet>
			<technique vocab="LOCAL" refid="05e81717-b5c1-552f-bafc-950a0f1ad2df">chromolithographs</technique>
		</techniqueSet>
		<titleSet>
			<title type="descriptive" pref="true" lang="en" script="Latn">1941 Advertisement calendar for A &amp; F Harvey</title>
		</titleSet>
		<worktypeSet>
			<worktype vocab="local" source="EXC" refid="8373d6f0-a4f0-5198-a092-25ff4af2c41f">posters</worktype>
			<worktype vocab="local" source="EXC" refid="37e0ef55-0bad-54b1-8ded-1082206c6016">calendars</worktype>
		</worktypeSet>
		<ext:heidicon>
			<ext:item type="f_description" status="0"  display="Full_Description">
				<ext:value>text-en:
A &amp; F Harvey
Merchants and cotton spinners</ext:value>
				<ext:value>text-en:
Counts up to 80's
Single Yarns
Double Yarns</ext:value>
				<ext:value>text-en:
Cone Yarns
Cheese Yarns
Cord &amp; Fancy Yarns</ext:value>
				<ext:value>text-en:
cone yarn
Madura Mills co. Ltd.
20 s
Madura</ext:value>
				<ext:value>text-en:
cheese yarn
Madura Mills Co. Ltd.
24 s
Madura
Cohal Mills Co. Ltd
Ring No</ext:value>
				<ext:value>text-en:
With the Compliments of
Madura Mills Co. Ltd.
[isncription on arch in central image]</ext:value>
				<ext:value>text-en:
The Arts School,
Madura.
[signature, central image]</ext:value>
				<ext:value>text-xx:
PLEASE ADD ORIGINAL LANGUAGE HERE [below central image, left]</ext:value>
				<ext:value>text-en:
Sree Meenakshisundareswarar, Madura
[below central image, middle]</ext:value>
				<ext:value>text-xx:
PLEASE ADD ORIGINAL LANGUAGE HERE
[below central image, right]</ext:value>
				<ext:value>text-en:
Madura Mills Company Limited.
Best Ring</ext:value>
				<ext:value>text-en:
Tinnevelly Turbine Twist
Tinnevelly Mills Company Limited
Ring No.</ext:value>
				<ext:value>text-xx:
PLEASE ADD ORIGINAL LANGUAGE HERE</ext:value>
				<ext:value>text-en:
Madura Mills Co. Ltd.
Tuticorn, Madura &amp; Ambasamudram, South India</ext:value>
				<ext:value>text-xx:
PLEASE ADD ORIGINAL LANGUAGE HERE</ext:value>
				<ext:value>text-en:
London Correspondents
Harvey Brothers
Agency Ltd.
34 Queen Anne's Gate
Westminster
London
S. W. 1</ext:value>
				<ext:value>text-en:
1941</ext:value>
				<ext:value>text-en:
Tele Address SONPAL.
Phone: B. B. 1519
Yarns available from
Messrs
Mooljee Girdhardass
5, Noormull Lohia Lane
&amp;
176, cross Street,
Calcutta.</ext:value>
				<ext:value>text-en:
Associated printers, Mount Road, Madras.</ext:value>
			</ext:item>
		</ext:heidicon>
		<ext:heidicon>
			<ext:item type="f_description" status="0"  display="Full_Commentary">
				<ext:value>explanatory comments/crosstagging:
/20080502_0504.jpg</ext:value>
			</ext:item>
		</ext:heidicon>
		<ext:heidicon>
			<ext:item type="t_ecs" status="0" display="comment:explanatory_comments_crosstagging">
				<ext:value type="text">/20080502_0504.jpg</ext:value>
				<ext:item type="agent">
					<ext:value type="role">Editor</ext:value>
					<ext:value type="name">PPColl_ed</ext:value>
					<ext:value type="agent-type">corporate</ext:value>
				</ext:item>
			</ext:item>
		</ext:heidicon>

		<ext:heidicon>
			<ext:item type="f_zusammenhang" status="0" display="zusammenhang">
				<ext:value>damaged</ext:value>
			</ext:item>
			<ext:item type="f_zusammenhang" status="0" display="zusammenhang">
				<ext:value>image cut on top and bottom</ext:value>
			</ext:item>
		</ext:heidicon>
		<ext:heidicon>
			<ext:item type="f_bildverknuepfung" vocab="" refid="" status="0" display="bildverknuepfung">
				<ext:value>http://heidicon.ub.uni-heidelberg.de/id/118514</ext:value>
				<ext:value>i_3e1952fd-d564-5db5-8adb-26ae6995783d</ext:value>
				<ext:value>detail view</ext:value>
			</ext:item>
		</ext:heidicon>
		<ext:heidicon>
			<ext:item type="f_id_heidicon" status="0" display="Heidicon image_id">
				<ext:value>http://heidicon.ub.uni-heidelberg.de/id/118512</ext:value>
				<ext:value>118512</ext:value>
			</ext:item>
		</ext:heidicon>
		<ext:heidicon>
			<ext:administrative type="heidicon2vra" date="2013-05-07T11:44:48">
			</ext:administrative>
		</ext:heidicon>
	</work>
</vra>