<vra xmlns="http://www.vraweb.org/vracore4.htm" xmlns:xsi="http://www.w3.org/2001/XMLSchema-instance" xsi:schemaLocation="http://www.vraweb.org/vracore4.htm http://cluster-schemas.uni-hd.de/vra-strictCluster.xsd" xmlns:hra="http://cluster-schemas.uni-hd.de" >
	<work id="w_78ad3bc8-d84f-547e-a04d-0d7b122ddb6d" source="EXC Priya Paul Collection" refid="c_b9827ec8-6b66-5d98-9f5e-ca12b58044c4">
		<agentSet>
			<agent>
				<name vocab="local" type="personal" refid="uuid-2d9170ef-2e41-537c-8a78-28b7be563ae7">Paul, Priya</name>
				<role vocab="marcrelator" code="col">Collector</role>
			</agent>
			<agent>
				<culture/>
				<name vocab="local" type="personal" refid="uuid-664f87db-93fc-53c2-bcc1-94d6a30fe186">Krishna</name>
				<role vocab="marcrelator" code="dpc">Depicted</role>
  			</agent>
		</agentSet>
 		<descriptionSet>
			<description source=" " lang="en" script="latn">Lord Krishna can be seen with flower garlands playing his flute, wearing a peacock`s feather and some jewellery.</description>
		</descriptionSet>
		<locationSet>
			<location type="repository">
				<name type="corporate" vocab="local">Delhi / The Priya Paul Collection of Popular Art</name>
				<refid/>
			</location>
			<location source="EXC" type="repository">
				<name type="geographic" vocab="local" refid="511">Delhi / The Priya Paul Collection of Popular Art</name>
			</location>
		</locationSet>
		<materialSet>
			<material vocab="LOCAL" refid="ce497196-b1b5-52ee-9f08-bb6627e56ef2" type="medium">paper (fiber product)</material>
		</materialSet>
		<measurementsSet>
			<notes>H 25 cm, W 17 cm, portrait</notes>
			<measurements type="height" unit="cm">25</measurements>
			<measurements type="width" unit="cm">17</measurements>
			<measurements shape="portrait" />
		</measurementsSet>
		<relationSet>
			<relation type="imageIs" relids="i_53fdac2c-e065-5d8d-9b16-1260a2de03c9" refid="119989" source="EXC Priya Paul Collection" pref="true"></relation>
		</relationSet>
		<rightsSet>
			<rights type="copyrighted">
				<rightsHolder/>
				<text>Copyrighted. Copyright with the original artists and publishers.</text>
			</rights>
		</rightsSet>
		<subjectSet>
			<subject source="EXC" vocab="LOCAL" refid="3b86ea94-9dbe-53d1-8beb-0c8f37a4416a">
				<term>halo</term>
			</subject>
			<subject source="EXC" vocab="LOCAL" refid="d04923d6-3e84-56f1-8bcb-ac9e50bfc215">
				<term>jewellery</term>
			</subject>
			<subject source="EXC" vocab="LOCAL" refid="6426548e-2d2c-5887-89d1-a6943b1abe35">
				<term>flute</term>
			</subject>
			<subject source="EXC" vocab="LOCAL" refid="55426fc7-dd87-5e47-9194-4be6a7da97d8">
				<term>recheck-Gerhard</term>
			</subject>
			<subject source="EXC" vocab="LOCAL" refid="aabbc697-061e-58d1-9daa-e21ad8ce9273">
				<term>peacock's feather</term>
			</subject>
			<subject source="EXC" vocab="LOCAL" refid="1ee21bd7-02f9-52c5-9a38-c87d76702f05">
				<term>flower garland</term>
			</subject>
		</subjectSet>
		<techniqueSet>
			<technique vocab="LOCAL" refid="05e81717-b5c1-552f-bafc-950a0f1ad2df">chromolithographs</technique>
		</techniqueSet>
		<titleSet>
			<title type="descriptive" pref="true" lang="en" script="latn">Garlands around the statue of Krishna</title>
		</titleSet>
		<worktypeSet>
			<worktype>posters</worktype>
		</worktypeSet>
		<hra:heidicon>
			<hra:item type="f_description" status="0"  display="Description">
				<hra:value>description-en:
Lord Krishna can be seen with flower garlands playing his flute, wearing a peacock`s feather and some jewellery. (gs)</hra:value>
			</hra:item>
		</hra:heidicon>
		<hra:heidicon>
			<hra:item type="f_zusammenhang" status="0" display="zusammenhang">
				<hra:value>good</hra:value>
			</hra:item>
		</hra:heidicon>
		<hra:heidicon>
			<hra:item type="f_id_heidicon" status="0" display="Heidicon image_id">
				<hra:value>http://heidicon.ub.uni-heidelberg.de/id/119989</hra:value>
				<hra:value>119989</hra:value>
			</hra:item>
		</hra:heidicon>
		<hra:heidicon>
			<hra:administrative type="heidicon2vra" date="2013-01-23 14:29:18">
			</hra:administrative>
		</hra:heidicon>
	</work>
</vra>