<vra xmlns="http://www.vraweb.org/vracore4.htm" xmlns:xsi="http://www.w3.org/2001/XMLSchema-instance" xsi:schemaLocation="http://www.vraweb.org/vracore4.htm http://cluster-schemas.uni-hd.de/vra-strictCluster.xsd" xmlns:ext="http://exist-db.org/vra/extension">
	<work id="w_bb3550a3-b063-56a3-99c2-414013a35552" source="EXC Priya Paul Collection" refid="c_b9827ec8-6b66-5d98-9f5e-ca12b58044c4">
		<agentSet>
			<agent>
				<name vocab="local" type="personal" refid="uuid-2d9170ef-2e41-537c-8a78-28b7be563ae7">Paul, Priya</name>
				<role vocab="marcrelator" type="code">col</role>
			</agent>
			<agent>
				<culture/>
				<name vocab="local" type="personal" refid="uuid-ddaa9cf1-f534-56a7-8e66-7534b767bfce">Nehru, Jawaharlal</name>
				<role vocab="marcrelator" type="code">art</role>
  			</agent>
			<agent>
				<culture/>
				<name vocab="local" type="personal" refid="uuid-6876fea7-eb89-510c-8778-db91c1e75c28">Gandhi, Indira</name>
				<role vocab="marcrelator" type="code">art</role>
  			</agent>
			<agent>
				<culture/>
				<name vocab="local" type="corporate" refid="uuid-5d356e46-6234-54ca-9c64-1998171fa3e0">Phoenix P. Works</name>
				<role vocab="marcrelator" type="code">cli</role>
  			</agent>
		</agentSet>
		<descriptionSet>
			<description lang="eng" script="Latn">
				<text>The image shows Jawaharlal Nehru, the first Prime Minister of independent India, standing behind his wife Kamala Nehru (on the left) and daughter Indira Gandhi (on the right). Both Kamala Nehru and Indisra Gandhi hold flowers in their hand.</text>
				<author>
					<name vocab="local" type="personal" refid="uuid-d4f4f076-3fb9-5544-95bf-29ba8cb16992">Schoenhofer, Gerhard</name>
					<role vocab="marcrelator" code="edt">Editor</role>
				</author>
				<author>
					<name vocab="local" type="personal" refid="uuid-dc8e6805-ec52-547a-993f-586ebd9681cc">Padmanabhan, Sridevi</name>
					<role vocab="marcrelator" code="edt">Editor</role>
				</author>
			</description>
			<description lang="eng" script="Latn" vocab="LOCAL" refid="687bd7ca-1185-5511-8938-1f351c94a5eb">
				<text>framing (processes)</text>
			</description>
		</descriptionSet>
		<inscriptionSet>
			<inscription>
				<text type="text" lang="eng">Phoenix P. Works, Ahmedabad</text>
			</inscription>
			<inscription>
				<text type="text" lang="eng">Copy Rt. No. 634</text>
			</inscription>
			<inscription>
				<text type="text" lang="eng">M. V. &amp; Co.</text>
			</inscription>
			<inscription>
				<text type="signature">M. V. &amp; Co.</text>
			</inscription>
		</inscriptionSet>
		<locationSet>
			<location source="EXC" type="repository">
				<name type="corporate" vocab="local" refid="uuid-1544a228-b79f-5cd9-a2ac-ff357ef3da5b">Delhi / The Priya Paul Collection of Popular Art</name>
			</location>
			<location source="EXC" type="repository">
				<name type="geographic" vocab="local" refid="">Delhi / The Priya Paul Collection of Popular Art</name>
			</location>
		</locationSet>
		<materialSet>
			<material vocab="LOCAL" refid="15f999c3-5f12-570c-a3c7-15678f571734" type="medium">cardboard</material>
		</materialSet>
		<measurementsSet>
			<notes>H 25 cm, W 20 cm, portrait</notes>
			<measurements type="height" unit="cm">25</measurements>
			<measurements type="width" unit="cm">20</measurements>
			<measurements shape="portrait" />
		</measurementsSet>
		<relationSet>
			<relation type="imageIs" relids="i_76f61f76-e9ec-5eed-b64e-5499a0dac108" refid="109790" source="EXC Priya Paul Collection" pref="true">general view</relation>
		</relationSet>
		<rightsSet>
			<rights type="copyrighted">
				<rightsHolder/>
				<text>Copyrighted. Copyright with the original artists and publishers.</text>
			</rights>
		</rightsSet>
		<stylePeriodSet>
		</stylePeriodSet>
		<subjectSet>
			<subject source="EXC" vocab="LOCAL" refid="44750451-00da-55b9-bd98-4036cdd413a2">
				<term type="conceptTopic">national leader</term>
			</subject>
			<subject source="EXC" vocab="LOCAL" refid="2afb3431-0ff7-51fc-aca3-559416741e66">
				<term type="descriptiveTopic">flowers (plants)</term>
			</subject>
			<subject source="EXC" vocab="LOCAL" refid="b64e275b-fe28-50db-a1e8-63a7fc7d0a85">
				<term type="descriptiveTopic">textile label</term>
			</subject>
			<subject source="EXC" vocab="LOCAL" refid="4b0eff81-18b6-5333-a35c-e688c999e2c9">
				<term type="descriptiveTopic">politicians</term>
			</subject>
			<subject source="EXC" vocab="LOCAL" refid="bb1d842f-4b29-5eee-a085-269d58cd6cb4">
				<term type="otherTopic">recheck</term>
			</subject>
			<subject source="EXC" vocab="LOCAL" refid="55426fc7-dd87-5e47-9194-4be6a7da97d8">
				<term type="otherTopic">recheck-Gerhard</term>
			</subject>
			<subject source="EXC" vocab="LOCAL" refid="1c5c689f-6b9d-5abd-86b9-5d71fb439820">
				<term type="conceptTopic">leaders (people)</term>
			</subject>
		</subjectSet>
		<techniqueSet>
			<technique vocab="LOCAL" refid="05e81717-b5c1-552f-bafc-950a0f1ad2df">chromolithographs</technique>
		</techniqueSet>
		<titleSet>
			<title type="descriptive" pref="true" lang="eng" script="Latn">Textile label by Phoenix P. Works</title>
		</titleSet>
		<worktypeSet>
			<worktype>labels</worktype>
		</worktypeSet>
		<ext:heidicon>
			<ext:item type="f_description" status="0"  display="Full_Description">
				<ext:value>text-en:
Phoenix P. Works, Ahmedabad</ext:value>
				<ext:value>text-en:
Copy Rt. No. 634</ext:value>
				<ext:value>description-en:
The image shows Jawaharlal Nehru, the first Prime Minister of independent India, standing behind his wife Kamala Nehru (on the left) and daughter Indira Gandhi (on the right). Both Kamala Nehru and Indisra Gandhi hold flowers in their hand.(gs/sp)</ext:value>
				<ext:value>text-en:
M. V. &amp; Co.</ext:value>
			</ext:item>
		</ext:heidicon>
		<ext:heidicon>
			<ext:item type="f_description" status="0"  display="Full_Commentary">
				<ext:value>explanatory comments/crosstagging:
Jawaharlal Nehru (1889 - 1964) was born in Kashmir and has been the longest serving Indian Prime Minister from 1947 till 1964. (gs)</ext:value>
			</ext:item>
		</ext:heidicon>
		<ext:heidicon>
			<ext:item type="t_ecs" status="0" display="comment:explanatory_comments_crosstagging">
				<ext:value type="text">Jawaharlal Nehru (1889 - 1964) was born in Kashmir and has been the longest serving Indian Prime Minister from 1947 till 1964.</ext:value>
				<ext:item type="agent">
					<ext:value type="role">Editor</ext:value>
					<ext:value type="name">Schoenhofer, Gerhard</ext:value>
					<ext:value type="agent-type">personal</ext:value>
					<ext:value type="refid">uuid-d4f4f076-3fb9-5544-95bf-29ba8cb16992</ext:value>
				</ext:item>
			</ext:item>
		</ext:heidicon>

		<ext:heidicon>
			<ext:item type="f_zusammenhang" status="0" display="zusammenhang">
				<ext:value>good</ext:value>
			</ext:item>
		</ext:heidicon>
		<ext:heidicon>
			<ext:item type="f_id_heidicon" status="0" display="Heidicon image_id">
				<ext:value>http://heidicon.ub.uni-heidelberg.de/id/109790</ext:value>
				<ext:value>109790</ext:value>
			</ext:item>
		</ext:heidicon>
		<ext:heidicon>
			<ext:administrative type="heidicon2vra" date="2014-01-15T17:56:54">
			</ext:administrative>
		</ext:heidicon>
	</work>
</vra>