<vra xmlns="http://www.vraweb.org/vracore4.htm" xmlns:xsi="http://www.w3.org/2001/XMLSchema-instance" xsi:schemaLocation="http://www.vraweb.org/vracore4.htm http://cluster-schemas.uni-hd.de/vra-strictCluster.xsd" xmlns:hra="http://cluster-schemas.uni-hd.de" >
	<work id="w_d5e7fda1-51e9-5218-b886-db1a118e461e" source="EXC Priya Paul Collection" refid="c_b9827ec8-6b66-5d98-9f5e-ca12b58044c4">
		<agentSet>
			<agent>
				<name vocab="local" type="personal" refid="uuid-2d9170ef-2e41-537c-8a78-28b7be563ae7">Paul, Priya</name>
				<role vocab="marcrelator" code="col">Collector</role>
			</agent>
			<agent>
				<culture/>
				<name vocab="local" type="personal" refid="uuid-732116f0-bd3e-5c22-b005-5e1c9b666a3d">Mahipal</name>
				<role vocab="marcrelator" code="art">Artist</role>
  			</agent>
			<agent>
				<culture/>
				<name vocab="local" type="personal" refid="uuid-30a002d0-b894-5702-8603-5121c5a28b92">Wadia, Homi</name>
				<role vocab="marcrelator" code="art">Artist</role>
  			</agent>
			<agent>
				<culture/>
				<name vocab="local" type="personal" refid="uuid-2ca870d1-591c-5d27-9c22-ef426432f658">Pahalwan, Vasantrao</name>
				<role vocab="marcrelator" code="art">Artist</role>
  			</agent>
		</agentSet>
 		<dateSet>
			<date type="creation">
				<earliestDate>1952</earliestDate>
				<latestDate>1952</latestDate>
			</date>
		</dateSet>
		<descriptionSet>
			<description source=" " lang="en" script="latn">The actor who is playing the role of the genie in this movie, is flying over a village holding Aladdins´ palace in his hands. The whole village is astonished about the genie flying in the sky and keeps track on him.</description>
		</descriptionSet>
		<inscriptionSet>
			<inscription>
				<text type="text" lang="en">Basant Pictures
presents</text>
			</inscription>
			<inscription>
				<text type="text" lang="en">Aladdin and the
Wonderful Lamp</text>
			</inscription>
			<inscription>
				<text type="text" lang="en">Wadia Brothers Production
Produced and Directed by
Homi Wadia</text>
			</inscription>
		</inscriptionSet>
		<locationSet>
			<location type="repository">
				<name type="corporate" vocab="local">Delhi / The Priya Paul Collection of Popular Art</name>
				<refid/>
			</location>
			<location source="EXC" type="repository">
				<name type="geographic" vocab="local" refid="511">Delhi / The Priya Paul Collection of Popular Art</name>
			</location>
		</locationSet>
		<measurementsSet>
			<notes>H 20 cm, W 30 cm, landscape</notes>
			<measurements type="height" unit="cm">20</measurements>
			<measurements type="width" unit="cm">30</measurements>
			<measurements shape="landscape" />
		</measurementsSet>
		<relationSet>
			<relation type="imageIs" relids="i_ac23a03a-6c9c-5f53-a5a0-e05cb04ac2be" refid="120167" source="EXC Priya Paul Collection" pref="true"></relation>
		</relationSet>
		<rightsSet>
			<rights type="copyrighted">
				<rightsHolder/>
				<text>Copyrighted. Copyright with the original artists and publishers.</text>
			</rights>
		</rightsSet>
		<stylePeriodSet>
			<stylePeriod>1950s</stylePeriod>
		</stylePeriodSet>
		<subjectSet>
			<subject source="EXC" vocab="LOCAL" refid="8373d6f0-a4f0-5198-a092-25ff4af2c41f">
				<term>poster</term>
			</subject>
			<subject source="EXC" vocab="LOCAL" refid="2b8821c7-f7f8-5bb8-952e-28194e2b3ac1">
				<term>lobby card</term>
			</subject>
			<subject source="EXC" vocab="LOCAL" refid="11be686d-58fc-534d-b2d0-141c871dff79">
				<term>Bollywood</term>
			</subject>
			<subject source="EXC" vocab="LOCAL" refid="38e3eaca-41e1-548e-9b95-398b391c8482">
				<term>Aladdin and the wonderful lamp</term>
			</subject>
			<subject source="EXC" vocab="LOCAL" refid="e2401328-5acd-5a23-ab09-2d44da01180f">
				<term>Hindi Film</term>
			</subject>
			<subject source="EXC" vocab="LOCAL" refid="92ec74b7-bfcb-5488-826a-b67395e147c6">
				<term>film</term>
			</subject>
			<subject source="EXC" vocab="LOCAL" refid="c07330ed-d4cd-50b7-be79-13a81c122ac0">
				<term>adaptation</term>
			</subject>
			<subject source="EXC" vocab="LOCAL" refid="c06dd31c-01d4-52fc-90ae-47a10d6519db">
				<term>recheck-Medialab</term>
			</subject>
			<subject source="EXC" vocab="LOCAL" refid="0fced42e-bef4-52b0-ad72-3602d3bce2f8">
				<term>film poster</term>
			</subject>
		</subjectSet>
		<techniqueSet>
			<technique vocab="LOCAL" refid="ea935392-d4c7-5801-968f-9da25f4a6780">gelatin silver prints</technique>
		</techniqueSet>
		<titleSet>
			<title type="descriptive" pref="true" lang="en" script="latn">Aladdin and the wonderful lamp</title>
		</titleSet>
		<worktypeSet>
			<worktype vocab="local" source="EXC" refid="794bef07-8b23-5ece-a426-60be06dcda8f">photographs</worktype>
			<worktype>posters</worktype>
		</worktypeSet>
		<hra:heidicon>
			<hra:item type="f_description" status="0"  display="Description">
				<hra:value>text-en:
Basant Pictures
presents</hra:value>
				<hra:value>text-en:
Aladdin and the
Wonderful Lamp</hra:value>
				<hra:value>text-en:
Wadia Brothers Production
Produced and Directed by
Homi Wadia</hra:value>
				<hra:value>description-en:
The actor who is playing the role of the genie in this movie, is flying over a village holding Aladdins´ palace in his hands. The whole village is astonished about the genie flying in the sky and keeps track on him. (gs)</hra:value>
			</hra:item>
		</hra:heidicon>
		<hra:heidicon>
			<hra:item type="f_description" status="0"  display="Kommentar">
				<hra:value>explanatory comments/crosstagging:
The movie &quot;Aladdin and his wonderful lamp&quot; was directed by Homi Wadia and released in 1952. Aladdin, as probably every reader knows, is the story of a good-hearted, if feckless, young man who comes into untold, unearned wealth and magical powers through command of a supernatural being: a djinni/genie arrives to do his will whenever he rubs a dirty old lamp he inadvertently acquired in an enchanted cave through a wicked magician’s trickery. (Rosie Thomas)(gs)</hra:value>
				<hra:value>explanatory comments/crosstagging:
This poster is a composite photograph, loosely based on the film’s final scene. The all-powerful djinni, the genie of the magic lamp, flies through dramatic storm clouds with Aladdin’s luxurious palace balanced precariously in his arms, whilst the crowd in the streets of Baghdad below celebrates Aladdin’s triumphant return to his mother’s side, his beautiful princess bride and entourage in tow. (Rosie Thomas)(gs)</hra:value>
				<hra:value>explanatory comments/crosstagging:
The image has curious resonances of the Ralli Brothers’ acrobat (check Picture-ID 109843): both are dreamscapes in which apparently magical flying promises to transport consumers out of the mundane world into an enchanted domain. In both cases, for viewers today, the burnished bronze rust stains and degraded image lend the sepia, silvery-brown and cream images a heightened quality of unreality and a magical golden glow. For its contemporary audience, the gigantic flying djinni in the silver-lined clouds would have made this instantly recognisable as a fantasy film. However, this publicity still did not have too much work to do – the story of Aladdin was as well known in 1950s India as it was in Europe. (Rosie Thomas)(gs)</hra:value>
				<hra:value>explanatory comments/crosstagging:
The success of Homi Wadia’s Aladdin kick-started a new vogue for fantasy films on the B and C circuits. By the mid-1950s these and costume films together accounted for around a third of all productions. (Rosie Thomas)(gs)</hra:value>
				<hra:value>related literature:
Irwin, Robert 1994. &quot;The Arabian Nights: A Companion&quot;. London: Allen Lane. (gs)</hra:value>
				<hra:value>related literature:
Marzolph, Ulrich 2006. &quot;Arabian Nights Reader&quot;. Detroit: Wayne State University Press. (gs)</hra:value>
				<hra:value>related literature:
Said, Edward 1995. &quot;Orientalism&quot;. London: Penguin Books. (gs)</hra:value>
				<hra:value>related literature:
Thomas, Rosie 2010. &quot;Still Magic. An Aladdin's Cave of 1950s B-Movie Fantasy&quot; http://www.tasveergharindia.net/cmsdesk/essay/103/index.html (22.11.2010) (gs)</hra:value>
				<hra:value>explanatory comments/crosstagging:
Movie poster. (ja)</hra:value>
			</hra:item>
		</hra:heidicon>
		<hra:heidicon>
			<hra:item type="t_rl" status="0" display="comment:related_literature">
				<hra:value>Thomas, Rosie 2010. &quot;Still Magic. An Aladdin's Cave of 1950s B-Movie Fantasy&quot; http://www.tasveergharindia.net/cmsdesk/essay/103/index.html (22.11.2010)</hra:value>
			</hra:item>
			<hra:item type="t_rl" status="0" display="comment:related_literature">
				<hra:value>Said, Edward 1995. &quot;Orientalism&quot;. London: Penguin Books.</hra:value>
			</hra:item>
			<hra:item type="t_rl" status="0" display="comment:related_literature">
				<hra:value>Marzolph, Ulrich 2006. &quot;Arabian Nights Reader&quot;. Detroit: Wayne State University Press.</hra:value>
			</hra:item>
			<hra:item type="t_rl" status="0" display="comment:related_literature">
				<hra:value>Irwin, Robert 1994. &quot;The Arabian Nights: A Companion&quot;. London: Allen Lane.</hra:value>
			</hra:item>
		</hra:heidicon>
		<hra:heidicon>
			<hra:item type="f_zusammenhang" status="0" display="zusammenhang">
				<hra:value>torn</hra:value>
			</hra:item>
		</hra:heidicon>
		<hra:heidicon>
			<hra:item type="f_personen" vocab="" refid="" status="0" display="personen">
				<hra:value>Mahipal</hra:value>
			</hra:item>
		</hra:heidicon>
		<hra:heidicon>
			<hra:item type="f_id_heidicon" status="0" display="Heidicon image_id">
				<hra:value>http://heidicon.ub.uni-heidelberg.de/id/120167</hra:value>
				<hra:value>120167</hra:value>
			</hra:item>
		</hra:heidicon>
		<hra:heidicon>
			<hra:administrative type="heidicon2vra" date="2013-01-23 14:37:53">
			</hra:administrative>
		</hra:heidicon>
	</work>
</vra>